{
  "gravity": -14.7,
  "bounds": [
    32,
    18
  ],
  "present_background": "present_background2",
  "past_background": "past_background2",
  "density": 0,
  "heavy_density": 10,
  "friction": 0.6,
  "restitution": 0.1,
  "bullet_offset": 0.7,
  "effect_volume": 0.8,
  "door": {
    "pos": [
      16.444,
      1.9700000000000022
    ],
    "size": [
      1.92,
      1.92
    ],
    "bodytype": "static",
    "density": 0,
    "friction": 0,
    "restitution": 0,
    "texture": "goal",
    "sensor": true,
    "nextlevel": 0,
    "space": 3
  },
  "avatar": {
    "pos": [
      16.228,
      8.899999999999999
    ],
    "shrink": [
      0.0216,
      0.01125
    ],
    "texture": "dude",
    "density": 1,
    "bodytype": "dynamic",
    "avatarstanding": "avatarstanding",
    "avatarcrouching": "avatarcrouching",
    "avatardashing": "avatardashing",
    "avatarfalling": "avatarfalling"
  },
  "turrets": {
    "turret12": {
      "pos": [
        27.944,
        11.61
      ],
      "shrink": [
        0.0168,
        0.021375
      ],
      "texture": "present_turret",
      "density": 1,
      "bodytype": "static",
      "entitytype": "present",
      "cooldown": 360,
      "direction": [
        -3,
        0
      ]
    },
    "turret13": {
      "pos": [
        5,
        11.19
      ],
      "shrink": [
        0.0168,
        0.021375
      ],
      "texture": "past_turret",
      "density": 1,
      "bodytype": "static",
      "entitytype": "past",
      "cooldown": 360,
      "direction": [
        3,
        0
      ]
    }
  },
  "capsules": {
    "presentcapsule34": {
      "name": "present_capsule",
      "pos": [
        23.88,
        10.47
      ],
      "bodytype": "static",
      "density": 0,
      "friction": 0.6,
      "restitution": 0.1,
      "texture": "present_capsule",
      "space": 1
    },
    "presentcapsule36": {
      "name": "present_capsule",
      "pos": [
        20.232,
        1.98
      ],
      "bodytype": "static",
      "density": 0,
      "friction": 0.6,
      "restitution": 0.1,
      "texture": "present_capsule",
      "space": 1
    },
    "pastcapsule41": {
      "name": "past_capsule",
      "pos": [
        6.088,
        10.02
      ],
      "bodytype": "static",
      "density": 0,
      "friction": 0.6,
      "restitution": 0.1,
      "texture": "past_capsule",
      "space": 2
    },
    "pastcapsule42": {
      "name": "past_capsule",
      "pos": [
        9.736,
        1.86
      ],
      "bodytype": "static",
      "density": 0,
      "friction": 0.6,
      "restitution": 0.1,
      "texture": "past_capsule",
      "space": 2
    }
  },
  "diamonds": {
    "bothdiamond35": {
      "name": "both_diamond",
      "pos": [
        14.824,
        12.21
      ],
      "bodytype": "static",
      "density": 0,
      "friction": 0.6,
      "restitution": 0.1,
      "texture": "both_diamond",
      "space": 3
    }
  },
  "rounds": {},
  "enemies": {
    "enemy10": {
      "pos": [
        25.224,
        9.54
      ],
      "shrink": [
        0.0168,
        0.021375
      ],
      "texture": "enemypast",
      "density": 1,
      "bodytype": "dynamic",
      "entitytype": "past",
      "cooldown": 360,
      "aitype": 1
    },
    "enemy11": {
      "pos": [
        7.752,
        8.49
      ],
      "shrink": [
        0.0168,
        0.021375
      ],
      "texture": "enemypresent",
      "density": 1,
      "bodytype": "dynamic",
      "entitytype": "present",
      "cooldown": 360,
      "aitype": 1
    }
  },
  "spikes": {},
  "talls": {
    "bothtall27": {
      "name": "both_tall",
      "pos": [
        15.24,
        4.29
      ],
      "bodytype": "static",
      "density": 0,
      "friction": 0.6,
      "restitution": 0.1,
      "texture": "both_tall",
      "space": 3
    }
  },
  "pillars": {},
  "longcapsules": {
    "presentlongcapsule43": {
      "name": "present_longcapsule",
      "pos": [
        5.16,
        5.88
      ],
      "bodytype": "static",
      "density": 0,
      "friction": 0.6,
      "restitution": 0.1,
      "texture": "present_longcapsule",
      "space": 1
    },
    "pastlongcapsule44": {
      "name": "past_longcapsule",
      "pos": [
        22.6,
        6.09
      ],
      "bodytype": "static",
      "density": 0,
      "friction": 0.6,
      "restitution": 0.1,
      "texture": "past_longcapsule",
      "space": 2
    }
  }
}