{
  "gravity": -14.7,
  "bounds": [
    32,
    18
  ],
  "present_background": "present_background1",
  "past_background": "past_background1",
  "door": {
    "pos": [
      29.052,
      15.14
    ],
    "size": [
      1.92,
      1.92
    ],
    "bodytype": "static",
    "density": 0,
    "friction": 0,
    "restitution": 0,
    "texture": "goal",
    "sensor": true,
    "nextlevel": 0,
    "space": 3
  },
  "avatar": {
    "pos": [
      4.54,
      3.8599999999999968
    ],
    "shrink": [
      0.0216,
      0.01125
    ],
    "texture": "dude",
    "density": 1,
    "bodytype": "dynamic",
    "avatarstanding": "avatarstanding",
    "avatarcrouching": "avatarcrouching",
    "avatardashing": "avatardashing",
    "avatarfalling": "avatarfalling"
  },
  "turrets": {
    "turret12": {
      "pos": [
        11.304,
        4.44
      ],
      "shrink": [
        0.0168,
        0.021375
      ],
      "texture": "present_turret",
      "density": 1,
      "bodytype": "static",
      "entitytype": "present",
      "cooldown": 360,
      "direction": [
        0,
        3
      ]
    },
    "turret14": {
      "pos": [
        19.784,
        5.37
      ],
      "shrink": [
        0.0168,
        0.021375
      ],
      "texture": "past_turret",
      "density": 1,
      "bodytype": "static",
      "entitytype": "past",
      "cooldown": 360,
      "direction": [
        0,
        3
      ]
    }
  },
  "capsules": {},
  "diamonds": {
    "bothdiamond28": {
      "name": "both_diamond",
      "pos": [
        23.72,
        10.71
      ],
      "bodytype": "static",
      "density": 0,
      "friction": 0.6,
      "restitution": 0.1,
      "texture": "both_diamond",
      "space": 3
    }
  },
  "rounds": {},
  "enemies": {
    "enemy13": {
      "pos": [
        25.096,
        14.55
      ],
      "shrink": [
        0.0168,
        0.021375
      ],
      "texture": "enemypast",
      "aitype": 1,
      "density": 1,
      "bodytype": "dynamic",
      "entitytype": "past",
      "cooldown": 300
    },
    "enemy15": {
      "pos": [
        25.032,
        13.8
      ],
      "shrink": [
        0.0168,
        0.021375
      ],
      "texture": "enemypresent",
      "aitype": 1,
      "density": 1,
      "bodytype": "dynamic",
      "entitytype": "present",
      "cooldown": 300
    }
  },
  "spikes": {},
  "talls": {},
  "pillars": {
    "bothpillar14":{
      "name":"both_pillar",
      "pos":[
        0.404,
        2.1
      ],
      "bodytype":"static",
      "density":0,
      "friction":0.6,
      "restitution":0.1,
      "texture":"both_pillar",
      "space":3
    }
  },
  "longcapsules": {
    "longcapsule6": {
    "name": "both_longcapsule",
    "pos": [
      1.004,
      1.8
    ],
    "bodytype": "static",
    "density": 0,
    "friction": 0.6,
    "restitution": 0.1,
    "texture": "both_longcapsule",
    "space": 3
  }
  }
}