{"gravity":-14.7,"bounds":[32,18],"present_background":"present_background3","past_background":"past_background3","door":{"pos":[15.644,14.15],"size":[1.92,1.92],"bodytype":"static","density":0,"friction":0,"restitution":0,"texture":"goal","sensor":true,"nextlevel":0,"space":3},"avatar":{"pos":[14.748000000000001,5.0299999999999985],"shrink":[0.0216,0.01125],"texture":"dude","density":1,"bodytype":"dynamic","avatarstanding":"avatarstanding","avatarcrouching":"avatarcrouching","avatardashing":"avatardashing","avatarfalling":"avatarfalling"},"turrets":{"turret1":{"pos":[1.96,1.68],"shrink":[0.0168,0.021375],"texture":"present_turret","density":1,"bodytype":"static","entitytype":"present","cooldown":360,"direction":[2.5,3]},"turret2":{"pos":[29.48,1.83],"shrink":[0.0168,0.021375],"texture":"past_turret","density":1,"bodytype":"static","entitytype":"past","cooldown":360,"direction":[-2.5,3]}},"capsules":{"capsule1":{"name":"present_capsule","pos":[28.168,5.07],"bodytype":"static","density":0,"friction":0.6,"restitution":0.1,"texture":"present_capsule","space":1},"capsule2":{"name":"past_capsule","pos":[0.488,4.68],"bodytype":"static","density":0,"friction":0.6,"restitution":0.1,"texture":"past_capsule","space":2}},"diamonds":{},"rounds":{},"enemies":{"enemy1":{"pos":[29.672,7.62],"shrink":[0.0168,0.021375],"texture":"enemypresent","aitype":1,"density":1,"bodytype":"dynamic","entitytype":"present","cooldown":275},"enemy2":{"pos":[1.864,7.77],"shrink":[0.0168,0.021375],"texture":"enemypast","aitype":1,"density":1,"bodytype":"dynamic","entitytype":"past","cooldown":275}},"spikes":{"spike1":{"pos":[11.476,5.2],"bodytype":"static","density":0,"friction":0.6,"restitution":0.1,"texture":"spikes","space":3,"angle":45},"spike2":{"pos":[10.548,5.14],"bodytype":"static","density":0,"friction":0.6,"restitution":0.1,"texture":"spikes","space":3,"angle":45},"spike3":{"pos":[9.78,5.2],"bodytype":"static","density":0,"friction":0.6,"restitution":0.1,"texture":"spikes","space":3,"angle":45},"spike4":{"pos":[19.38,5.32],"bodytype":"static","density":0,"friction":0.6,"restitution":0.1,"texture":"spikes","space":3,"angle":45},"spike5":{"pos":[20.276,5.170000000000002],"bodytype":"static","density":0,"friction":0.6,"restitution":0.1,"texture":"spikes","space":3,"angle":45},"spike6":{"pos":[21.172,5.26],"bodytype":"static","density":0,"friction":0.6,"restitution":0.1,"texture":"spikes","space":3,"angle":45},"spike7":{"pos":[14.228,9.370000000000001],"bodytype":"static","density":0,"friction":0.6,"restitution":0.1,"texture":"spikes","space":3,"angle":225},"spike8":{"pos":[15.348,9.700000000000001],"bodytype":"static","density":0,"friction":0.6,"restitution":0.1,"texture":"spikes","space":3,"angle":225},"spike9":{"pos":[16.372,9.55],"bodytype":"static","density":0,"friction":0.6,"restitution":0.1,"texture":"spikes","space":3,"angle":225},"spike10":{"pos":[17.332,9.610000000000001],"bodytype":"static","density":0,"friction":0.6,"restitution":0.1,"texture":"spikes","space":3,"angle":225}},"talls":{},"pillars":{},"longcapsules":{"longcapsule1":{"name":"both_longcapsule","pos":[6.6,9.72],"bodytype":"static","density":0,"friction":0.6,"restitution":0.1,"texture":"both_longcapsule","space":3},"longcapsule2":{"name":"both_longcapsule","pos":[10.6,9.809999999999999],"bodytype":"static","density":0,"friction":0.6,"restitution":0.1,"texture":"both_longcapsule","space":3},"longcapsule3":{"name":"both_longcapsule","pos":[15.464,9.84],"bodytype":"static","density":0,"friction":0.6,"restitution":0.1,"texture":"both_longcapsule","space":3},"longcapsule4":{"name":"both_longcapsule","pos":[19.88,9.87],"bodytype":"static","density":0,"friction":0.6,"restitution":0.1,"texture":"both_longcapsule","space":3},"longcapsule5":{"name":"both_longcapsule","pos":[6.76,3.39],"bodytype":"static","density":0,"friction":0.6,"restitution":0.1,"texture":"both_longcapsule","space":3},"longcapsule6":{"name":"both_longcapsule","pos":[11.048,3.45],"bodytype":"static","density":0,"friction":0.6,"restitution":0.1,"texture":"both_longcapsule","space":3},"longcapsule7":{"name":"both_longcapsule","pos":[14.984,3.42],"bodytype":"static","density":0,"friction":0.6,"restitution":0.1,"texture":"both_longcapsule","space":3},"longcapsule8":{"name":"both_longcapsule","pos":[19.784,3.42],"bodytype":"static","density":0,"friction":0.6,"restitution":0.1,"texture":"both_longcapsule","space":3}}}